provenance/__init__.py
provenance/_commonstore.py
provenance/_config.py
provenance/_dependencies.py
provenance/_logging.py
provenance/_version.py
provenance/alembic.ini
provenance/artifact_hasher.py
provenance/blobstores.py
provenance/core.py
provenance/google_storage.py
provenance/hashing.py
provenance/models.py
provenance/repos.py
provenance/serializers.py
provenance/test_serializers.py
provenance/utils.py
provenance/migrations/README
provenance/migrations/env.py
provenance/migrations/script.py.mako
provenance/migrations/versions/e0317ab07ba4_initial_schema.py
provenance/sftp/__init__.py
provenance/vis/__init__.py
provenance/vis/utils.py
provenance-0.14.1.dist-info/LICENSE.txt
provenance-0.14.1.dist-info/METADATA
provenance-0.14.1.dist-info/WHEEL
provenance-0.14.1.dist-info/top_level.txt
provenance-0.14.1.dist-info/RECORD
