Metadata-Version: 2.1
Name: provenance
Version: 0.14.1
Summary: Provenance and caching library for functions, built for creating lightweight machine learning pipelines.
Home-page: http://github.com/bmabey/provenance
Author: Ben Mabey
Author-email: ben@benmabey.com
License: MIT
Platform: UNKNOWN
Classifier: Development Status :: 4 - Beta
Classifier: Intended Audience :: Developers
Classifier: Intended Audience :: Science/Research
Classifier: License :: OSI Approved :: MIT License
Provides-Extra: sftp
Provides-Extra: google_storage
Provides-Extra: vis
